run80by24/server/__init__.py
run80by24/server/__main__.py
run80by24/server/app.py
run80by24/server/aqueue.py
run80by24/server/banner.py
run80by24/server/clients.py
run80by24/server/conf.py
run80by24/server/exceptions.py
run80by24/server/routes.py
run80by24/server/session.py
run80by24/server/state.py
run80by24_server-0.2.0.dist-info/DESCRIPTION.rst
run80by24_server-0.2.0.dist-info/METADATA
run80by24_server-0.2.0.dist-info/RECORD
run80by24_server-0.2.0.dist-info/WHEEL
run80by24_server-0.2.0.dist-info/entry_points.txt
run80by24_server-0.2.0.dist-info/metadata.json
run80by24_server-0.2.0.dist-info/top_level.txt
